{
    "rootName": "todos",
    "rootEntity": {
        "id": "t",
        "name": "todo",
        "columns": {
            "todoId": "todo_id",
            "title": {
                "column": "title",
                "type": "string"
            },
            "description": {
                "column": "description",
                "type": "string"
            },
            "completed": "completed",
            "createdAt": "created_at",
            "updatedAt": "updated_at",
            "commentCount": "comment_count"
        }
    },
    "nestedEntities": [
        {
            "id": "u",
            "name": "user",
            "parentId": "t",
            "propertyName": "user",
            "relationshipType": "object",
            "columns": {
                "userId": "user_id",
                "userName": {
                    "column": "user_name",
                    "type": "string"
                },
                "email": {
                    "column": "email",
                    "type": "string"
                }
            }
        },
        {
            "id": "c",
            "name": "category",
            "parentId": "t",
            "propertyName": "category",
            "relationshipType": "object",
            "columns": {
                "categoryId": "category_id",
                "categoryName": {
                    "column": "category_name",
                    "type": "string"
                },
                "color": {
                    "column": "color",
                    "type": "string"
                }
            }
        }
    ]
}